<?xml version="1.0" encoding="UTF-8" ?>
<!DOCTYPE struts PUBLIC
    "-//Apache Software Foundation//DTD Struts Configuration 2.3//EN"
    "http://struts.apache.org/dtds/struts-2.3.dtd">
    
    <struts>
    		<package name="index" namespace="/api" extends="json-default">
    			<action name="AddCart" class="addCart" method="execute">
    				<result type="json">
    					<param name="root">jsonResult</param>
    				</result>
    			</action>
    			<action name="ChangeCart" class="changeCart" method="execute">
    				<result type="json">
    					<param name="root">jsonResult</param>
    				</result>
    			</action>
    			<action name="GetCart" class="getCart" method="execute">
    				<result type="json">
    					<param name="root">jsonResult</param>
    				</result>
    			</action>
    			<action name="Reservate" class="reservate" method="execute">
    				<result type="json">
    					<param name="root">jsonResult</param>
    				</result>
    			</action>
    			<action name="ChangeInfo" class="changeInfo" method="execute">
    				<result type="json">
    					<param name="root">jsonResult</param>
    				</result>
    			</action>
    			<action name="ToCash" class="toCash" method="execute">
    				<result type="json">
    					<param name="root">jsonResult</param>
    				</result>
    			</action>
    			<action name="ChangeBankcard" class="changeBankcard" method="execute">
    				<result type="json">
    					<param name="root">jsonResult</param>
    				</result>
    			</action>
    			<action name="CardRecharge" class="cardRecharge" method="execute">
    				<result type="json">
    					<param name="root">jsonResult</param>
    				</result>
    			</action>
    			<action name="CashRecharge" class="cashRecharge" method="execute">
    				<result type="json">
    					<param name="root">jsonResult</param>
    				</result>
    			</action>
    			<action name="UpdatePlan" class="updatePlan" method="execute">
    				<result type="json">
    					<param name="root">jsonResult</param>
    				</result>
    			</action>
    			<action name="DeletePlan" class="deletePlan" method="execute">
    				<result type="json">
    					<param name="root">jsonResult</param>
    				</result>
    			</action>
    			<action name="AddPlan" class="addPlan" method="execute">
    				<result type="json">
    					<param name="root">jsonResult</param>
    				</result>
    			</action>
    			<action name="UpdateStore" class="updateStore" method="execute">
    				<result type="json">
    					<param name="root">jsonResult</param>
    				</result>
    			</action>
    			<action name="DeleteStore" class="deleteStore" method="execute">
    				<result type="json">
    					<param name="root">jsonResult</param>
    				</result>
    			</action>
    			<action name="AddStore" class="addStore" method="execute">
    				<result type="json">
    					<param name="root">jsonResult</param>
    				</result>
    			</action>
    			<action name="ListStore" class="listStore" method="execute">
    				<result type="json">
    					<param name="root">jsonResult</param>
    				</result>
    			</action>
    			<action name="UpdateEmployee" class="updateEmployee" method="execute">
    				<result type="json">
    					<param name="root">jsonResult</param>
    				</result>
    			</action>
    			<action name="DeleteEmployee" class="deleteEmployee" method="execute">
    				<result type="json">
    					<param name="root">jsonResult</param>
    				</result>
    			</action>
    			<action name="AddEmployee" class="addEmployee" method="execute">
    				<result type="json">
    					<param name="root">jsonResult</param>
    				</result>
    			</action>
    			<action name="PassPlan" class="passPlan" method="execute">
    				<result type="json">
    					<param name="root">jsonResult</param>
    				</result>
    			</action>
    			<!-- 不通过的计划备注 -->
    			<action name="RejectPlan" class="rejectPlan" method="execute">
    				<result type="json">
    					<param name="root">jsonResult</param>
    				</result>
    			</action>
    			<!-- 销售界面新增商品 -->
    			<action name="AddCommodity" class="addCommodity" method="execute">
    				<result type="json">
    					<param name="root">jsonResult</param>
    				</result>
    			</action>
    			<!-- 销售界面删除商品 -->
    			<action name="DelCommodity" class="delCommodity" method="execute">
    				<result type="json">
    					<param name="root">jsonResult</param>
    				</result>
    			</action>
    			<action name="CheckMember" class="checkMember" method="execute">
    				<result type="json">
    					<param name="root">jsonResult</param>
    				</result>
    			</action>
    			<action name="PayByCard" class="payByCard" method="execute">
    				<result type="json">
    					<param name="root">jsonResult</param>
    				</result>
    			</action>
    			<action name="PayByCash" class="payByCash" method="execute">
    				<result type="json">
    					<param name="root">jsonResult</param>
    				</result>
    			</action>
    			<action name="CancelMember" class="cancelMember" method="execute">
    				<result type="json">
    					<param name="root">jsonResult</param>
    				</result>
    			</action>
    			<!-- 清空一个店员 -->
    			<action name="EmpEmptyOne" class="empEmptyOne" method="execute">
    				<result type="json">
    					<param name="root">jsonResult</param>
    				</result>
    			</action>
    			<!-- 撤销删除店员 -->
    			<action name="EmployeeUnDel" class="employeeUnDel" method="execute">
    				<result type="json">
    					<param name="root">jsonResult</param>
    				</result>
    			</action>
    			<!-- 清空多个店员 -->
    			<action name="EmpEmptyAll" class="empEmptyAll" method="execute">
    				<result type="json">
    					<param name="root">jsonResult</param>
    				</result>
    			</action>
    			<!-- 获得已删除的店员 -->
    			<action name="EmpListDeleteGet" class="empListDeleteGet" method="execute">
    				<result type="json">
    					<param name="root">jsonResult</param>
    				</result>
    			</action>
    			<!-- 清空一个店面 -->
    			<action name="StoreEmptyOne" class="storeEmptyOne" method="execute">
    				<result type="json">
    					<param name="root">jsonResult</param>
    				</result>
    			</action>
    			<!-- 撤销删除一个店面 -->
    			<action name="StoreUnDel" class="storeUnDel" method="execute">
    				<result type="json">
    					<param name="root">jsonResult</param>
    				</result>
    			</action>
    			<!-- 清空多个店面 -->
    			<action name="StoreEmptyAll" class="storeEmptyAll" method="execute">
    				<result type="json">
    					<param name="root">jsonResult</param>
    				</result>
    			</action>
    			<!-- 获得已删除的店面-->
    			<action name="StoreListDeleteGet" class="storeListDeleteGet" method="execute">
    				<result type="json">
    					<param name="root">jsonResult</param>
    				</result>
    			</action>
    			<!-- 清空一个计划 -->
    			<action name="PlanEmptyOne" class="planEmptyOne" method="execute">
    				<result type="json">
    					<param name="root">jsonResult</param>
    				</result>
    			</action>
    			<!-- 撤销删除一个计划 -->
    			<action name="PlanUnDel" class="planUnDel" method="execute">
    				<result type="json">
    					<param name="root">jsonResult</param>
    				</result>
    			</action>
    			<!-- 清空多个计划 -->
    			<action name="PlanEmptyAll" class="planEmptyAll" method="execute">
    				<result type="json">
    					<param name="root">jsonResult</param>
    				</result>
    			</action>
    			<!-- 获得已删除的计划-->
    			<action name="PlanListDeleteGet" class="planListDeleteGet" method="execute">
    				<result type="json">
    					<param name="root">jsonResult</param>
    				</result>
    			</action>
    			<!-- 发送信息-->
    			<action name="SendMessage" class="sendMessage" method="execute">
    				<result type="json">
    					<param name="root">jsonResult</param>
    				</result>
    			</action>
    			<!-- 删除一条信息-->
    			<action name="MessageDel" class="messageDel" method="execute">
    				<result type="json">
    					<param name="root">jsonResult</param>
    				</result>
    			</action>
    			<!-- 已读一条信息-->
    			<action name="ReadMessage" class="readMessage" method="execute">
    				<result type="json">
    					<param name="root">jsonResult</param>
    				</result>
    			</action>
    			<!-- 撤销删除一条信息-->
    			<action name="UndeleteMessage" class="undeleteMessage" method="execute">
    				<result type="json">
    					<param name="root">jsonResult</param>
    				</result>
    			</action>
    			<!-- 清空一条信息-->
    			<action name="MesEmptyOne" class="mesEmptyOne" method="execute">
    				<result type="json">
    					<param name="root">jsonResult</param>
    				</result>
    			</action>
    			<!-- 清空所有未读信息-->
    			<action name="MesEmptyAll" class="mesEmptyAll" method="execute">
    				<result type="json">
    					<param name="root">jsonResult</param>
    				</result>
    			</action>
    			<!-- 获得已删除消息-->
    			<action name="MesDeleteGet" class="mesDeleteGet" method="execute">
    				<result type="json">
    					<param name="root">jsonResult</param>
    				</result>
    			</action>
    			<!-- 获得未读消息-->
    			<action name="MesUnreadGet" class="mesUnreadGet" method="execute">
    				<result type="json">
    					<param name="root">jsonResult</param>
    				</result>
    			</action>
    			<!-- 获得已读消息-->
    			<action name="MesReadGet" class="mesReadGet" method="execute">
    				<result type="json">
    					<param name="root">jsonResult</param>
    				</result>
    			</action>
    		</package>		
    </struts>